{
	"id":"chambresEtage2",
	"background":"css/img/chambresEtage2.svg.png",
	"listImage":[
		{
			"id":"porte201",
			"src":"css/img/porteChambre.png",
			"x":40,
			"y":74,
			"listOn":[
				{
					"verb":"aller",
					"action":{
						"funct":"message",
						"message":"La porte est ferme a clef"
					}
				},
				{
					"verb":"utiliser",
					"with":"key201",
					"action":{
						"funct":"setState",
						"state":"open"
					}
				}
			],
			"listState":{
				"open":{
					"src":"css/img/porteChambreOpened.png",
					"listOn":[
						{
							"verb":"aller",
							"action":{
								"funct":"loadRoom",
								"room":"room201"
							}
						}
					]
				}
			}
		},
		{
			"id":"porte202",
			"src":"css/img/porteChambre.png",
			"x":240,
			"y":74,
			"listOn":[
				{
					"verb":"aller",
					"action":{
						"funct":"message",
						"message":"La porte est ferme a clef"
					}
				},
				{
					"verb":"utiliser",
					"with":"key202",
					"action":{
						"funct":"setState",
						"state":"open"
					}
				}
			],
			"listState":{
				"open":{
					"src":"css/img/porteChambreOpened.png",
					"listOn":[
						{
							"verb":"aller",
							"action":{
								"funct":"loadRoom",
								"room":"room202"
							}
						}
					]
				}
			}
		},
		{
			"id":"porte203",
			"src":"css/img/porteChambre.png",
			"x":440,
			"y":74,
			"listOn":[
				{
					"verb":"aller",
					"action":{
						"funct":"message",
						"message":"La porte est ferme a clef"
					}
				}
			]
		},

		{
			"id":"leftArrow",
			"x":20,"y":340,
			"src":"css/img/leftArrow.png",
			"listOn":[
				{
					"verb":"aller",
					"action":{
						"funct":"loadRoom",
						"room":"ascenseur"
					}
				}
			],
			"listState":{
				"open":{
					"src":"css/img/porteChambreOpened.png",
					"listOn":[
						{
							"verb":"aller",
							"action":{
								"funct":"loadRoom",
								"room":"room103"
							}
						}
					]
				}
			}
		}
	]
}
